aws_solutions_constructs/aws_lambda_sagemaker/__init__.py
aws_solutions_constructs/aws_lambda_sagemaker/py.typed
aws_solutions_constructs/aws_lambda_sagemaker/_jsii/__init__.py
aws_solutions_constructs/aws_lambda_sagemaker/_jsii/aws-lambda-sagemaker@1.72.0.jsii.tgz
aws_solutions_constructs.aws_lambda_sagemaker-1.72.0.dist-info/METADATA
aws_solutions_constructs.aws_lambda_sagemaker-1.72.0.dist-info/WHEEL
aws_solutions_constructs.aws_lambda_sagemaker-1.72.0.dist-info/top_level.txt
aws_solutions_constructs.aws_lambda_sagemaker-1.72.0.dist-info/RECORD
