Metadata-Version: 2.1
Name: aws-solutions-constructs.aws-lambda-sagemaker
Version: 1.72.0
Summary: CDK Constructs for AWS Lambda to AWS Sagemaker integration.
Home-page: https://github.com/awslabs/aws-solutions-constructs.git
Author: Amazon Web Services
License: Apache-2.0
Project-URL: Source, https://github.com/awslabs/aws-solutions-constructs.git
Platform: UNKNOWN
Classifier: Intended Audience :: Developers
Classifier: Operating System :: OS Independent
Classifier: Programming Language :: JavaScript
Classifier: Programming Language :: Python :: 3 :: Only
Classifier: Programming Language :: Python :: 3.6
Classifier: Programming Language :: Python :: 3.7
Classifier: Programming Language :: Python :: 3.8
Classifier: Typing :: Typed
Classifier: License :: OSI Approved
Requires-Python: >=3.6
Requires-Dist: aws-cdk.aws-ec2 (==1.72.0)
Requires-Dist: aws-cdk.aws-iam (==1.72.0)
Requires-Dist: aws-cdk.aws-kms (==1.72.0)
Requires-Dist: aws-cdk.aws-lambda (==1.72.0)
Requires-Dist: aws-cdk.aws-sagemaker (==1.72.0)
Requires-Dist: aws-cdk.core (==1.72.0)
Requires-Dist: aws-solutions-constructs.core (==1.72.0)
Requires-Dist: constructs (<4.0.0,>=3.2.0)
Requires-Dist: jsii (<2.0.0,>=1.14.1)
Requires-Dist: publication (>=0.0.3)
